shai_tix/__init__.py
shai_tix/_version.py
shai_tix/api.py
shai_tix/cli.py
shai_tix/constants.py
shai_tix/db.py
shai_tix/paths.py
shai_tix/title_codec.py
shai_tix/tix.py
shai_tix/utils.py
shai_tix/vendor/__init__.py
shai_tix/vendor/pytest_cov_helper.py
shai_tix-0.1.3.dist-info/AUTHORS.rst
shai_tix-0.1.3.dist-info/LICENSE.txt
shai_tix-0.1.3.dist-info/METADATA
shai_tix-0.1.3.dist-info/WHEEL
shai_tix-0.1.3.dist-info/entry_points.txt
shai_tix-0.1.3.dist-info/RECORD
